dj_watchfiles/__init__.py
dj_watchfiles/py.typed
dj_watchfiles/watch.py
dj_watchfiles-2.0.1.dist-info/METADATA
dj_watchfiles-2.0.1.dist-info/WHEEL
dj_watchfiles-2.0.1.dist-info/licenses/LICENSE
dj_watchfiles-2.0.1.dist-info/RECORD
