Metadata-Version: 2.4
Name: dj-watchfiles
Version: 2.0.1
Summary: Use watchfiles in Django’s autoreloader.
Project-URL: Homepage, https://github.com/xshapira/dj-watchfiles
Project-URL: Documentation, https://github.com/xshapira/dj-watchfiles
Author-email: Max Shapira <m@xshapira.com>
Maintainer-email: Max Shapira <m@xshapira.com>
License-Expression: MIT
License-File: LICENSE
Classifier: Development Status :: 5 - Production/Stable
Classifier: Framework :: Django :: 4.2
Classifier: Framework :: Django :: 5.0
Classifier: Framework :: Django :: 5.1
Classifier: Intended Audience :: Developers
Classifier: License :: OSI Approved :: MIT License
Classifier: Natural Language :: English
Classifier: Operating System :: OS Independent
Classifier: Programming Language :: Python :: 3 :: Only
Classifier: Programming Language :: Python :: 3.9
Classifier: Programming Language :: Python :: 3.10
Classifier: Programming Language :: Python :: 3.11
Classifier: Programming Language :: Python :: 3.12
Classifier: Programming Language :: Python :: 3.13
Classifier: Programming Language :: Python :: Implementation :: CPython
Classifier: Typing :: Typed
Requires-Python: >=3.9
Requires-Dist: django>=4.2
Requires-Dist: pytest
Requires-Dist: watchfiles
